__init__.py
ingest_data.py
nonstandardcode.py
score.py
train.py
example_package_Akalya-0.0.1.dist-info/METADATA
example_package_Akalya-0.0.1.dist-info/WHEEL
example_package_Akalya-0.0.1.dist-info/top_level.txt
example_package_Akalya-0.0.1.dist-info/RECORD
